{".class":"MypyFile","_fullname":"dimod.binary.pybqm","future_import_flags":[],"is_partial_stub_package":false,"is_stub":false,"names":{".class":"SymbolTable","Any":{".class":"SymbolTableNode","cross_ref":"typing.Any","kind":"Gdef"},"ArrayLike":{".class":"SymbolTableNode","cross_ref":"numpy._typing._array_like.ArrayLike","kind":"Gdef"},"Callable":{".class":"SymbolTableNode","cross_ref":"typing.Callable","kind":"Gdef"},"Collection":{".class":"SymbolTableNode","cross_ref":"typing.Collection","kind":"Gdef"},"DTypeLike":{".class":"SymbolTableNode","cross_ref":"numpy._typing._dtype_like.DTypeLike","kind":"Gdef"},"Dict":{".class":"SymbolTableNode","cross_ref":"typing.Dict","kind":"Gdef"},"Iterator":{".class":"SymbolTableNode","cross_ref":"typing.Iterator","kind":"Gdef"},"KeysView":{".class":"SymbolTableNode","cross_ref":"typing.KeysView","kind":"Gdef"},"Mapping":{".class":"SymbolTableNode","cross_ref":"typing.Mapping","kind":"Gdef"},"Optional":{".class":"SymbolTableNode","cross_ref":"typing.Optional","kind":"Gdef"},"Tuple":{".class":"SymbolTableNode","cross_ref":"typing.Tuple","kind":"Gdef"},"Variable":{".class":"SymbolTableNode","cross_ref":"dimod.typing.Variable","kind":"Gdef"},"Vartype":{".class":"SymbolTableNode","cross_ref":"dimod.vartypes.Vartype","kind":"Gdef"},"VartypeLike":{".class":"SymbolTableNode","cross_ref":"dimod.vartypes.VartypeLike","kind":"Gdef"},"__annotations__":{".class":"SymbolTableNode","kind":"Gdef","node":{".class":"Var","flags":["is_ready"],"fullname":"dimod.binary.pybqm.__annotations__","name":"__annotations__","type":{".class":"Instance","args":["builtins.str",{".class":"AnyType","missing_import_name":null,"source_any":null,"type_of_any":6}],"extra_attrs":null,"type_ref":"builtins.dict"}}},"__doc__":{".class":"SymbolTableNode","kind":"Gdef","node":{".class":"Var","flags":["is_ready"],"fullname":"dimod.binary.pybqm.__doc__","name":"__doc__","type":"builtins.str"}},"__file__":{".class":"SymbolTableNode","kind":"Gdef","node":{".class":"Var","flags":["is_ready"],"fullname":"dimod.binary.pybqm.__file__","name":"__file__","type":"builtins.str"}},"__name__":{".class":"SymbolTableNode","kind":"Gdef","node":{".class":"Var","flags":["is_ready"],"fullname":"dimod.binary.pybqm.__name__","name":"__name__","type":"builtins.str"}},"__package__":{".class":"SymbolTableNode","kind":"Gdef","node":{".class":"Var","flags":["is_ready"],"fullname":"dimod.binary.pybqm.__package__","name":"__package__","type":"builtins.str"}},"__spec__":{".class":"SymbolTableNode","kind":"Gdef","node":{".class":"Var","flags":["is_ready"],"fullname":"dimod.binary.pybqm.__spec__","name":"__spec__","type":"_frozen_importlib.ModuleSpec"}},"as_samples":{".class":"SymbolTableNode","cross_ref":"dimod.sampleset.as_samples","kind":"Gdef"},"as_vartype":{".class":"SymbolTableNode","cross_ref":"dimod.vartypes.as_vartype","kind":"Gdef"},"copy":{".class":"SymbolTableNode","cross_ref":"copy","kind":"Gdef"},"iter_safe_relabels":{".class":"SymbolTableNode","cross_ref":"dimod.utilities.iter_safe_relabels","kind":"Gdef"},"np":{".class":"SymbolTableNode","cross_ref":"numpy","kind":"Gdef"},"pyBQM":{".class":"SymbolTableNode","kind":"Gdef","node":{".class":"TypeInfo","_promote":[],"abstract_attributes":[],"alt_promote":null,"bases":["builtins.object"],"dataclass_transform_spec":null,"declared_metaclass":null,"defn":{".class":"ClassDef","fullname":"dimod.binary.pybqm.pyBQM","name":"pyBQM","type_vars":[]},"deletable_attributes":[],"deprecated":null,"flags":[],"fullname":"dimod.binary.pybqm.pyBQM","has_param_spec_type":false,"metaclass_type":null,"metadata":{},"module_name":"dimod.binary.pybqm","mro":["dimod.binary.pybqm.pyBQM","builtins.object"],"names":{".class":"SymbolTable","__copy__":{".class":"SymbolTableNode","kind":"Mdef","node":{".class":"FuncDef","abstract_status":0,"arg_kinds":[0],"arg_names":["self"],"dataclass_transform_spec":null,"deprecated":null,"flags":[],"fullname":"dimod.binary.pybqm.pyBQM.__copy__","name":"__copy__","type":null}},"__init__":{".class":"SymbolTableNode","kind":"Mdef","node":{".class":"FuncDef","abstract_status":0,"arg_kinds":[0,0],"arg_names":["self","vartype"],"dataclass_transform_spec":null,"deprecated":null,"flags":[],"fullname":"dimod.binary.pybqm.pyBQM.__init__","name":"__init__","type":{".class":"CallableType","arg_kinds":[0,0],"arg_names":["self","vartype"],"arg_types":["dimod.binary.pybqm.pyBQM",{".class":"TypeAliasType","args":[],"type_ref":"dimod.vartypes.VartypeLike"}],"bound_args":[],"def_extras":{"first_arg":"self"},"fallback":"builtins.function","from_concatenate":false,"implicit":false,"imprecise_arg_kinds":false,"is_ellipsis_args":false,"name":"__init__ of pyBQM","ret_type":{".class":"NoneType"},"type_guard":null,"type_is":null,"unpack_kwargs":false,"variables":[]}}},"_adj":{".class":"SymbolTableNode","implicit":true,"kind":"Mdef","node":{".class":"Var","flags":["explicit_self_type","is_ready","is_inferred"],"fullname":"dimod.binary.pybqm.pyBQM._adj","name":"_adj","type":{".class":"Instance","args":["typing.Hashable",{".class":"Instance","args":["typing.Hashable",{".class":"AnyType","missing_import_name":null,"source_any":null,"type_of_any":2}],"extra_attrs":null,"type_ref":"builtins.dict"}],"extra_attrs":null,"type_ref":"builtins.dict"}}},"_vartype":{".class":"SymbolTableNode","implicit":true,"kind":"Mdef","node":{".class":"Var","flags":["is_inferred"],"fullname":"dimod.binary.pybqm.pyBQM._vartype","name":"_vartype","type":"dimod.vartypes.Vartype"}},"add_linear":{".class":"SymbolTableNode","kind":"Mdef","node":{".class":"FuncDef","abstract_status":0,"arg_kinds":[0,0,0],"arg_names":["self","v","bias"],"dataclass_transform_spec":null,"deprecated":null,"flags":[],"fullname":"dimod.binary.pybqm.pyBQM.add_linear","name":"add_linear","type":{".class":"CallableType","arg_kinds":[0,0,0],"arg_names":["self","v","bias"],"arg_types":["dimod.binary.pybqm.pyBQM","typing.Hashable",{".class":"AnyType","missing_import_name":null,"source_any":null,"type_of_any":2}],"bound_args":[],"def_extras":{"first_arg":"self"},"fallback":"builtins.function","from_concatenate":false,"implicit":false,"imprecise_arg_kinds":false,"is_ellipsis_args":false,"name":"add_linear of pyBQM","ret_type":{".class":"AnyType","missing_import_name":null,"source_any":null,"type_of_any":1},"type_guard":null,"type_is":null,"unpack_kwargs":false,"variables":[]}}},"add_linear_equality_constraint":{".class":"SymbolTableNode","kind":"Mdef","node":{".class":"FuncDef","abstract_status":0,"arg_kinds":[0,2,4],"arg_names":["self","args","kwargs"],"dataclass_transform_spec":null,"deprecated":null,"flags":[],"fullname":"dimod.binary.pybqm.pyBQM.add_linear_equality_constraint","name":"add_linear_equality_constraint","type":null}},"add_linear_from_array":{".class":"SymbolTableNode","kind":"Mdef","node":{".class":"FuncDef","abstract_status":0,"arg_kinds":[0,0],"arg_names":["self","linear"],"dataclass_transform_spec":null,"deprecated":null,"flags":[],"fullname":"dimod.binary.pybqm.pyBQM.add_linear_from_array","name":"add_linear_from_array","type":{".class":"CallableType","arg_kinds":[0,0],"arg_names":["self","linear"],"arg_types":["dimod.binary.pybqm.pyBQM",{".class":"TypeAliasType","args":[],"type_ref":"numpy._typing._array_like.ArrayLike"}],"bound_args":[],"def_extras":{"first_arg":"self"},"fallback":"builtins.function","from_concatenate":false,"implicit":false,"imprecise_arg_kinds":false,"is_ellipsis_args":false,"name":"add_linear_from_array of pyBQM","ret_type":{".class":"AnyType","missing_import_name":null,"source_any":null,"type_of_any":1},"type_guard":null,"type_is":null,"unpack_kwargs":false,"variables":[]}}},"add_quadratic":{".class":"SymbolTableNode","kind":"Mdef","node":{".class":"FuncDef","abstract_status":0,"arg_kinds":[0,0,0,0],"arg_names":["self","u","v","bias"],"dataclass_transform_spec":null,"deprecated":null,"flags":[],"fullname":"dimod.binary.pybqm.pyBQM.add_quadratic","name":"add_quadratic","type":{".class":"CallableType","arg_kinds":[0,0,0,0],"arg_names":["self","u","v","bias"],"arg_types":["dimod.binary.pybqm.pyBQM","typing.Hashable","typing.Hashable",{".class":"AnyType","missing_import_name":null,"source_any":null,"type_of_any":2}],"bound_args":[],"def_extras":{"first_arg":"self"},"fallback":"builtins.function","from_concatenate":false,"implicit":false,"imprecise_arg_kinds":false,"is_ellipsis_args":false,"name":"add_quadratic of pyBQM","ret_type":{".class":"AnyType","missing_import_name":null,"source_any":null,"type_of_any":1},"type_guard":null,"type_is":null,"unpack_kwargs":false,"variables":[]}}},"add_quadratic_from_dense":{".class":"SymbolTableNode","kind":"Mdef","node":{".class":"FuncDef","abstract_status":0,"arg_kinds":[0,0],"arg_names":["self","quadratic"],"dataclass_transform_spec":null,"deprecated":null,"flags":[],"fullname":"dimod.binary.pybqm.pyBQM.add_quadratic_from_dense","name":"add_quadratic_from_dense","type":{".class":"CallableType","arg_kinds":[0,0],"arg_names":["self","quadratic"],"arg_types":["dimod.binary.pybqm.pyBQM",{".class":"TypeAliasType","args":[],"type_ref":"numpy._typing._array_like.ArrayLike"}],"bound_args":[],"def_extras":{"first_arg":"self"},"fallback":"builtins.function","from_concatenate":false,"implicit":false,"imprecise_arg_kinds":false,"is_ellipsis_args":false,"name":"add_quadratic_from_dense of pyBQM","ret_type":{".class":"AnyType","missing_import_name":null,"source_any":null,"type_of_any":1},"type_guard":null,"type_is":null,"unpack_kwargs":false,"variables":[]}}},"add_variable":{".class":"SymbolTableNode","kind":"Mdef","node":{".class":"FuncDef","abstract_status":0,"arg_kinds":[0,1,1],"arg_names":["self","v","bias"],"dataclass_transform_spec":null,"deprecated":null,"flags":[],"fullname":"dimod.binary.pybqm.pyBQM.add_variable","name":"add_variable","type":{".class":"CallableType","arg_kinds":[0,1,1],"arg_names":["self","v","bias"],"arg_types":["dimod.binary.pybqm.pyBQM",{".class":"UnionType","items":["typing.Hashable",{".class":"NoneType"}],"uses_pep604_syntax":false},{".class":"AnyType","missing_import_name":null,"source_any":null,"type_of_any":2}],"bound_args":[],"def_extras":{"first_arg":"self"},"fallback":"builtins.function","from_concatenate":false,"implicit":false,"imprecise_arg_kinds":false,"is_ellipsis_args":false,"name":"add_variable of pyBQM","ret_type":"typing.Hashable","type_guard":null,"type_is":null,"unpack_kwargs":false,"variables":[]}}},"change_vartype":{".class":"SymbolTableNode","kind":"Mdef","node":{".class":"FuncDef","abstract_status":0,"arg_kinds":[0,0],"arg_names":["self","vartype"],"dataclass_transform_spec":null,"deprecated":null,"flags":[],"fullname":"dimod.binary.pybqm.pyBQM.change_vartype","name":"change_vartype","type":{".class":"CallableType","arg_kinds":[0,0],"arg_names":["self","vartype"],"arg_types":["dimod.binary.pybqm.pyBQM",{".class":"TypeAliasType","args":[],"type_ref":"dimod.vartypes.VartypeLike"}],"bound_args":[],"def_extras":{"first_arg":"self"},"fallback":"builtins.function","from_concatenate":false,"implicit":false,"imprecise_arg_kinds":false,"is_ellipsis_args":false,"name":"change_vartype of pyBQM","ret_type":"dimod.binary.pybqm.pyBQM","type_guard":null,"type_is":null,"unpack_kwargs":false,"variables":[]}}},"clear":{".class":"SymbolTableNode","kind":"Mdef","node":{".class":"FuncDef","abstract_status":0,"arg_kinds":[0],"arg_names":["self"],"dataclass_transform_spec":null,"deprecated":null,"flags":[],"fullname":"dimod.binary.pybqm.pyBQM.clear","name":"clear","type":{".class":"CallableType","arg_kinds":[0],"arg_names":["self"],"arg_types":["dimod.binary.pybqm.pyBQM"],"bound_args":[],"def_extras":{"first_arg":"self"},"fallback":"builtins.function","from_concatenate":false,"implicit":false,"imprecise_arg_kinds":false,"is_ellipsis_args":false,"name":"clear of pyBQM","ret_type":{".class":"NoneType"},"type_guard":null,"type_is":null,"unpack_kwargs":false,"variables":[]}}},"degree":{".class":"SymbolTableNode","kind":"Mdef","node":{".class":"FuncDef","abstract_status":0,"arg_kinds":[0,0],"arg_names":["self","v"],"dataclass_transform_spec":null,"deprecated":null,"flags":[],"fullname":"dimod.binary.pybqm.pyBQM.degree","name":"degree","type":{".class":"CallableType","arg_kinds":[0,0],"arg_names":["self","v"],"arg_types":["dimod.binary.pybqm.pyBQM","typing.Hashable"],"bound_args":[],"def_extras":{"first_arg":"self"},"fallback":"builtins.function","from_concatenate":false,"implicit":false,"imprecise_arg_kinds":false,"is_ellipsis_args":false,"name":"degree of pyBQM","ret_type":"builtins.int","type_guard":null,"type_is":null,"unpack_kwargs":false,"variables":[]}}},"dtype":{".class":"SymbolTableNode","kind":"Mdef","node":{".class":"Decorator","func":{".class":"FuncDef","abstract_status":0,"arg_kinds":[0],"arg_names":["self"],"dataclass_transform_spec":null,"deprecated":null,"flags":["is_property","is_decorated"],"fullname":"dimod.binary.pybqm.pyBQM.dtype","name":"dtype","type":{".class":"CallableType","arg_kinds":[0],"arg_names":["self"],"arg_types":["dimod.binary.pybqm.pyBQM"],"bound_args":[],"def_extras":{"first_arg":"self"},"fallback":"builtins.function","from_concatenate":false,"implicit":false,"imprecise_arg_kinds":false,"is_ellipsis_args":false,"name":"dtype of pyBQM","ret_type":{".class":"Instance","args":[{".class":"AnyType","missing_import_name":null,"source_any":null,"type_of_any":4}],"extra_attrs":null,"type_ref":"numpy.dtype"},"type_guard":null,"type_is":null,"unpack_kwargs":false,"variables":[]}},"is_overload":false,"var":{".class":"Var","flags":["is_initialized_in_class","is_property","is_ready","is_inferred"],"fullname":"dimod.binary.pybqm.pyBQM.dtype","name":"dtype","type":{".class":"CallableType","arg_kinds":[0],"arg_names":["self"],"arg_types":["dimod.binary.pybqm.pyBQM"],"bound_args":[],"def_extras":{"first_arg":"self"},"fallback":"builtins.function","from_concatenate":false,"implicit":false,"imprecise_arg_kinds":false,"is_ellipsis_args":false,"name":"dtype of pyBQM","ret_type":{".class":"Instance","args":[{".class":"AnyType","missing_import_name":null,"source_any":null,"type_of_any":4}],"extra_attrs":null,"type_ref":"numpy.dtype"},"type_guard":null,"type_is":null,"unpack_kwargs":false,"variables":[]}}}},"energies":{".class":"SymbolTableNode","kind":"Mdef","node":{".class":"FuncDef","abstract_status":0,"arg_kinds":[0,0,1],"arg_names":["self","samples_like","dtype"],"dataclass_transform_spec":null,"deprecated":null,"flags":[],"fullname":"dimod.binary.pybqm.pyBQM.energies","name":"energies","type":{".class":"CallableType","arg_kinds":[0,0,1],"arg_names":["self","samples_like","dtype"],"arg_types":["dimod.binary.pybqm.pyBQM",{".class":"AnyType","missing_import_name":null,"source_any":null,"type_of_any":1},{".class":"TypeAliasType","args":[],"type_ref":"numpy._typing._dtype_like.DTypeLike"}],"bound_args":[],"def_extras":{"first_arg":"self"},"fallback":"builtins.function","from_concatenate":false,"implicit":false,"imprecise_arg_kinds":false,"is_ellipsis_args":false,"name":"energies of pyBQM","ret_type":{".class":"AnyType","missing_import_name":null,"source_any":null,"type_of_any":1},"type_guard":null,"type_is":null,"unpack_kwargs":false,"variables":[]}}},"get_linear":{".class":"SymbolTableNode","kind":"Mdef","node":{".class":"FuncDef","abstract_status":0,"arg_kinds":[0,0],"arg_names":["self","v"],"dataclass_transform_spec":null,"deprecated":null,"flags":[],"fullname":"dimod.binary.pybqm.pyBQM.get_linear","name":"get_linear","type":{".class":"CallableType","arg_kinds":[0,0],"arg_names":["self","v"],"arg_types":["dimod.binary.pybqm.pyBQM","typing.Hashable"],"bound_args":[],"def_extras":{"first_arg":"self"},"fallback":"builtins.function","from_concatenate":false,"implicit":false,"imprecise_arg_kinds":false,"is_ellipsis_args":false,"name":"get_linear of pyBQM","ret_type":{".class":"AnyType","missing_import_name":null,"source_any":null,"type_of_any":2},"type_guard":null,"type_is":null,"unpack_kwargs":false,"variables":[]}}},"get_quadratic":{".class":"SymbolTableNode","kind":"Mdef","node":{".class":"FuncDef","abstract_status":0,"arg_kinds":[0,0,0,1],"arg_names":["self","u","v","default"],"dataclass_transform_spec":null,"deprecated":null,"flags":[],"fullname":"dimod.binary.pybqm.pyBQM.get_quadratic","name":"get_quadratic","type":{".class":"CallableType","arg_kinds":[0,0,0,1],"arg_names":["self","u","v","default"],"arg_types":["dimod.binary.pybqm.pyBQM","typing.Hashable","typing.Hashable",{".class":"UnionType","items":[{".class":"AnyType","missing_import_name":null,"source_any":null,"type_of_any":2},{".class":"NoneType"}],"uses_pep604_syntax":false}],"bound_args":[],"def_extras":{"first_arg":"self"},"fallback":"builtins.function","from_concatenate":false,"implicit":false,"imprecise_arg_kinds":false,"is_ellipsis_args":false,"name":"get_quadratic of pyBQM","ret_type":{".class":"AnyType","missing_import_name":null,"source_any":null,"type_of_any":2},"type_guard":null,"type_is":null,"unpack_kwargs":false,"variables":[]}}},"is_linear":{".class":"SymbolTableNode","kind":"Mdef","node":{".class":"FuncDef","abstract_status":0,"arg_kinds":[0],"arg_names":["self"],"dataclass_transform_spec":null,"deprecated":null,"flags":[],"fullname":"dimod.binary.pybqm.pyBQM.is_linear","name":"is_linear","type":{".class":"CallableType","arg_kinds":[0],"arg_names":["self"],"arg_types":["dimod.binary.pybqm.pyBQM"],"bound_args":[],"def_extras":{"first_arg":"self"},"fallback":"builtins.function","from_concatenate":false,"implicit":false,"imprecise_arg_kinds":false,"is_ellipsis_args":false,"name":"is_linear of pyBQM","ret_type":"builtins.bool","type_guard":null,"type_is":null,"unpack_kwargs":false,"variables":[]}}},"iter_neighborhood":{".class":"SymbolTableNode","kind":"Mdef","node":{".class":"FuncDef","abstract_status":0,"arg_kinds":[0,0],"arg_names":["self","v"],"dataclass_transform_spec":null,"deprecated":null,"flags":[],"fullname":"dimod.binary.pybqm.pyBQM.iter_neighborhood","name":"iter_neighborhood","type":{".class":"CallableType","arg_kinds":[0,0],"arg_names":["self","v"],"arg_types":["dimod.binary.pybqm.pyBQM","typing.Hashable"],"bound_args":[],"def_extras":{"first_arg":"self"},"fallback":"builtins.function","from_concatenate":false,"implicit":false,"imprecise_arg_kinds":false,"is_ellipsis_args":false,"name":"iter_neighborhood of pyBQM","ret_type":{".class":"Instance","args":[{".class":"AnyType","missing_import_name":null,"source_any":null,"type_of_any":2}],"extra_attrs":null,"type_ref":"typing.Iterator"},"type_guard":null,"type_is":null,"unpack_kwargs":false,"variables":[]}}},"iter_quadratic":{".class":"SymbolTableNode","kind":"Mdef","node":{".class":"FuncDef","abstract_status":0,"arg_kinds":[0],"arg_names":["self"],"dataclass_transform_spec":null,"deprecated":null,"flags":[],"fullname":"dimod.binary.pybqm.pyBQM.iter_quadratic","name":"iter_quadratic","type":{".class":"CallableType","arg_kinds":[0],"arg_names":["self"],"arg_types":["dimod.binary.pybqm.pyBQM"],"bound_args":[],"def_extras":{"first_arg":"self"},"fallback":"builtins.function","from_concatenate":false,"implicit":false,"imprecise_arg_kinds":false,"is_ellipsis_args":false,"name":"iter_quadratic of pyBQM","ret_type":{".class":"Instance","args":[{".class":"TupleType","implicit":false,"items":["typing.Hashable","typing.Hashable",{".class":"AnyType","missing_import_name":null,"source_any":null,"type_of_any":2}],"partial_fallback":{".class":"Instance","args":[{".class":"AnyType","missing_import_name":null,"source_any":null,"type_of_any":6}],"extra_attrs":null,"type_ref":"builtins.tuple"}}],"extra_attrs":null,"type_ref":"typing.Iterator"},"type_guard":null,"type_is":null,"unpack_kwargs":false,"variables":[]}}},"nbytes":{".class":"SymbolTableNode","kind":"Mdef","node":{".class":"FuncDef","abstract_status":0,"arg_kinds":[0,2,4],"arg_names":["self","args","kwargs"],"dataclass_transform_spec":null,"deprecated":null,"flags":[],"fullname":"dimod.binary.pybqm.pyBQM.nbytes","name":"nbytes","type":{".class":"CallableType","arg_kinds":[0,2,4],"arg_names":["self","args","kwargs"],"arg_types":["dimod.binary.pybqm.pyBQM",{".class":"AnyType","missing_import_name":null,"source_any":null,"type_of_any":1},{".class":"AnyType","missing_import_name":null,"source_any":null,"type_of_any":1}],"bound_args":[],"def_extras":{"first_arg":"self"},"fallback":"builtins.function","from_concatenate":false,"implicit":false,"imprecise_arg_kinds":false,"is_ellipsis_args":false,"name":"nbytes of pyBQM","ret_type":{".class":"UninhabitedType"},"type_guard":null,"type_is":null,"unpack_kwargs":false,"variables":[]}}},"num_interactions":{".class":"SymbolTableNode","kind":"Mdef","node":{".class":"FuncDef","abstract_status":0,"arg_kinds":[0],"arg_names":["self"],"dataclass_transform_spec":null,"deprecated":null,"flags":[],"fullname":"dimod.binary.pybqm.pyBQM.num_interactions","name":"num_interactions","type":{".class":"CallableType","arg_kinds":[0],"arg_names":["self"],"arg_types":["dimod.binary.pybqm.pyBQM"],"bound_args":[],"def_extras":{"first_arg":"self"},"fallback":"builtins.function","from_concatenate":false,"implicit":false,"imprecise_arg_kinds":false,"is_ellipsis_args":false,"name":"num_interactions of pyBQM","ret_type":"builtins.int","type_guard":null,"type_is":null,"unpack_kwargs":false,"variables":[]}}},"num_variables":{".class":"SymbolTableNode","kind":"Mdef","node":{".class":"FuncDef","abstract_status":0,"arg_kinds":[0],"arg_names":["self"],"dataclass_transform_spec":null,"deprecated":null,"flags":[],"fullname":"dimod.binary.pybqm.pyBQM.num_variables","name":"num_variables","type":{".class":"CallableType","arg_kinds":[0],"arg_names":["self"],"arg_types":["dimod.binary.pybqm.pyBQM"],"bound_args":[],"def_extras":{"first_arg":"self"},"fallback":"builtins.function","from_concatenate":false,"implicit":false,"imprecise_arg_kinds":false,"is_ellipsis_args":false,"name":"num_variables of pyBQM","ret_type":"builtins.int","type_guard":null,"type_is":null,"unpack_kwargs":false,"variables":[]}}},"offset":{".class":"SymbolTableNode","implicit":true,"kind":"Mdef","node":{".class":"Var","flags":["is_inferred"],"fullname":"dimod.binary.pybqm.pyBQM.offset","name":"offset","type":"builtins.int"}},"reduce_linear":{".class":"SymbolTableNode","kind":"Mdef","node":{".class":"FuncDef","abstract_status":0,"arg_kinds":[0,0,1],"arg_names":["self","function","initializer"],"dataclass_transform_spec":null,"deprecated":null,"flags":[],"fullname":"dimod.binary.pybqm.pyBQM.reduce_linear","name":"reduce_linear","type":{".class":"CallableType","arg_kinds":[0,0,1],"arg_names":["self","function","initializer"],"arg_types":["dimod.binary.pybqm.pyBQM",{".class":"CallableType","arg_kinds":[2,4],"arg_names":[null,null],"arg_types":[{".class":"AnyType","missing_import_name":null,"source_any":null,"type_of_any":4},{".class":"AnyType","missing_import_name":null,"source_any":null,"type_of_any":4}],"bound_args":[],"def_extras":{},"fallback":"builtins.function","from_concatenate":false,"implicit":false,"imprecise_arg_kinds":false,"is_ellipsis_args":true,"name":null,"ret_type":{".class":"AnyType","missing_import_name":null,"source_any":null,"type_of_any":4},"type_guard":null,"type_is":null,"unpack_kwargs":false,"variables":[]},{".class":"UnionType","items":[{".class":"AnyType","missing_import_name":null,"source_any":null,"type_of_any":2},{".class":"NoneType"}],"uses_pep604_syntax":false}],"bound_args":[],"def_extras":{"first_arg":"self"},"fallback":"builtins.function","from_concatenate":false,"implicit":false,"imprecise_arg_kinds":false,"is_ellipsis_args":false,"name":"reduce_linear of pyBQM","ret_type":{".class":"AnyType","missing_import_name":null,"source_any":null,"type_of_any":2},"type_guard":null,"type_is":null,"unpack_kwargs":false,"variables":[]}}},"reduce_neighborhood":{".class":"SymbolTableNode","kind":"Mdef","node":{".class":"FuncDef","abstract_status":0,"arg_kinds":[0,0,0,1],"arg_names":["self","v","function","initializer"],"dataclass_transform_spec":null,"deprecated":null,"flags":[],"fullname":"dimod.binary.pybqm.pyBQM.reduce_neighborhood","name":"reduce_neighborhood","type":{".class":"CallableType","arg_kinds":[0,0,0,1],"arg_names":["self","v","function","initializer"],"arg_types":["dimod.binary.pybqm.pyBQM","typing.Hashable",{".class":"CallableType","arg_kinds":[2,4],"arg_names":[null,null],"arg_types":[{".class":"AnyType","missing_import_name":null,"source_any":null,"type_of_any":4},{".class":"AnyType","missing_import_name":null,"source_any":null,"type_of_any":4}],"bound_args":[],"def_extras":{},"fallback":"builtins.function","from_concatenate":false,"implicit":false,"imprecise_arg_kinds":false,"is_ellipsis_args":true,"name":null,"ret_type":{".class":"AnyType","missing_import_name":null,"source_any":null,"type_of_any":4},"type_guard":null,"type_is":null,"unpack_kwargs":false,"variables":[]},{".class":"UnionType","items":[{".class":"AnyType","missing_import_name":null,"source_any":null,"type_of_any":2},{".class":"NoneType"}],"uses_pep604_syntax":false}],"bound_args":[],"def_extras":{"first_arg":"self"},"fallback":"builtins.function","from_concatenate":false,"implicit":false,"imprecise_arg_kinds":false,"is_ellipsis_args":false,"name":"reduce_neighborhood of pyBQM","ret_type":{".class":"AnyType","missing_import_name":null,"source_any":null,"type_of_any":2},"type_guard":null,"type_is":null,"unpack_kwargs":false,"variables":[]}}},"reduce_quadratic":{".class":"SymbolTableNode","kind":"Mdef","node":{".class":"FuncDef","abstract_status":0,"arg_kinds":[0,0,1],"arg_names":["self","function","initializer"],"dataclass_transform_spec":null,"deprecated":null,"flags":[],"fullname":"dimod.binary.pybqm.pyBQM.reduce_quadratic","name":"reduce_quadratic","type":{".class":"CallableType","arg_kinds":[0,0,1],"arg_names":["self","function","initializer"],"arg_types":["dimod.binary.pybqm.pyBQM",{".class":"CallableType","arg_kinds":[2,4],"arg_names":[null,null],"arg_types":[{".class":"AnyType","missing_import_name":null,"source_any":null,"type_of_any":4},{".class":"AnyType","missing_import_name":null,"source_any":null,"type_of_any":4}],"bound_args":[],"def_extras":{},"fallback":"builtins.function","from_concatenate":false,"implicit":false,"imprecise_arg_kinds":false,"is_ellipsis_args":true,"name":null,"ret_type":{".class":"AnyType","missing_import_name":null,"source_any":null,"type_of_any":4},"type_guard":null,"type_is":null,"unpack_kwargs":false,"variables":[]},{".class":"UnionType","items":[{".class":"AnyType","missing_import_name":null,"source_any":null,"type_of_any":2},{".class":"NoneType"}],"uses_pep604_syntax":false}],"bound_args":[],"def_extras":{"first_arg":"self"},"fallback":"builtins.function","from_concatenate":false,"implicit":false,"imprecise_arg_kinds":false,"is_ellipsis_args":false,"name":"reduce_quadratic of pyBQM","ret_type":{".class":"AnyType","missing_import_name":null,"source_any":null,"type_of_any":2},"type_guard":null,"type_is":null,"unpack_kwargs":false,"variables":[]}}},"relabel_variables":{".class":"SymbolTableNode","kind":"Mdef","node":{".class":"FuncDef","abstract_status":0,"arg_kinds":[0,0],"arg_names":["self","mapping"],"dataclass_transform_spec":null,"deprecated":null,"flags":[],"fullname":"dimod.binary.pybqm.pyBQM.relabel_variables","name":"relabel_variables","type":{".class":"CallableType","arg_kinds":[0,0],"arg_names":["self","mapping"],"arg_types":["dimod.binary.pybqm.pyBQM",{".class":"Instance","args":["typing.Hashable","typing.Hashable"],"extra_attrs":null,"type_ref":"typing.Mapping"}],"bound_args":[],"def_extras":{"first_arg":"self"},"fallback":"builtins.function","from_concatenate":false,"implicit":false,"imprecise_arg_kinds":false,"is_ellipsis_args":false,"name":"relabel_variables of pyBQM","ret_type":{".class":"AnyType","missing_import_name":null,"source_any":null,"type_of_any":1},"type_guard":null,"type_is":null,"unpack_kwargs":false,"variables":[]}}},"relabel_variables_as_integers":{".class":"SymbolTableNode","kind":"Mdef","node":{".class":"FuncDef","abstract_status":0,"arg_kinds":[0],"arg_names":["self"],"dataclass_transform_spec":null,"deprecated":null,"flags":[],"fullname":"dimod.binary.pybqm.pyBQM.relabel_variables_as_integers","name":"relabel_variables_as_integers","type":{".class":"CallableType","arg_kinds":[0],"arg_names":["self"],"arg_types":["dimod.binary.pybqm.pyBQM"],"bound_args":[],"def_extras":{"first_arg":"self"},"fallback":"builtins.function","from_concatenate":false,"implicit":false,"imprecise_arg_kinds":false,"is_ellipsis_args":false,"name":"relabel_variables_as_integers of pyBQM","ret_type":{".class":"Instance","args":["builtins.int","typing.Hashable"],"extra_attrs":null,"type_ref":"typing.Mapping"},"type_guard":null,"type_is":null,"unpack_kwargs":false,"variables":[]}}},"remove_interaction":{".class":"SymbolTableNode","kind":"Mdef","node":{".class":"FuncDef","abstract_status":0,"arg_kinds":[0,0,0],"arg_names":["self","u","v"],"dataclass_transform_spec":null,"deprecated":null,"flags":[],"fullname":"dimod.binary.pybqm.pyBQM.remove_interaction","name":"remove_interaction","type":{".class":"CallableType","arg_kinds":[0,0,0],"arg_names":["self","u","v"],"arg_types":["dimod.binary.pybqm.pyBQM","typing.Hashable","typing.Hashable"],"bound_args":[],"def_extras":{"first_arg":"self"},"fallback":"builtins.function","from_concatenate":false,"implicit":false,"imprecise_arg_kinds":false,"is_ellipsis_args":false,"name":"remove_interaction of pyBQM","ret_type":{".class":"AnyType","missing_import_name":null,"source_any":null,"type_of_any":1},"type_guard":null,"type_is":null,"unpack_kwargs":false,"variables":[]}}},"remove_variable":{".class":"SymbolTableNode","kind":"Mdef","node":{".class":"FuncDef","abstract_status":0,"arg_kinds":[0,1],"arg_names":["self","v"],"dataclass_transform_spec":null,"deprecated":null,"flags":[],"fullname":"dimod.binary.pybqm.pyBQM.remove_variable","name":"remove_variable","type":{".class":"CallableType","arg_kinds":[0,1],"arg_names":["self","v"],"arg_types":["dimod.binary.pybqm.pyBQM",{".class":"UnionType","items":["typing.Hashable",{".class":"NoneType"}],"uses_pep604_syntax":false}],"bound_args":[],"def_extras":{"first_arg":"self"},"fallback":"builtins.function","from_concatenate":false,"implicit":false,"imprecise_arg_kinds":false,"is_ellipsis_args":false,"name":"remove_variable of pyBQM","ret_type":"typing.Hashable","type_guard":null,"type_is":null,"unpack_kwargs":false,"variables":[]}}},"resize":{".class":"SymbolTableNode","kind":"Mdef","node":{".class":"FuncDef","abstract_status":0,"arg_kinds":[0,0],"arg_names":["self","n"],"dataclass_transform_spec":null,"deprecated":null,"flags":[],"fullname":"dimod.binary.pybqm.pyBQM.resize","name":"resize","type":{".class":"CallableType","arg_kinds":[0,0],"arg_names":["self","n"],"arg_types":["dimod.binary.pybqm.pyBQM","builtins.int"],"bound_args":[],"def_extras":{"first_arg":"self"},"fallback":"builtins.function","from_concatenate":false,"implicit":false,"imprecise_arg_kinds":false,"is_ellipsis_args":false,"name":"resize of pyBQM","ret_type":{".class":"AnyType","missing_import_name":null,"source_any":null,"type_of_any":1},"type_guard":null,"type_is":null,"unpack_kwargs":false,"variables":[]}}},"set_linear":{".class":"SymbolTableNode","kind":"Mdef","node":{".class":"FuncDef","abstract_status":0,"arg_kinds":[0,0,0],"arg_names":["self","v","bias"],"dataclass_transform_spec":null,"deprecated":null,"flags":[],"fullname":"dimod.binary.pybqm.pyBQM.set_linear","name":"set_linear","type":{".class":"CallableType","arg_kinds":[0,0,0],"arg_names":["self","v","bias"],"arg_types":["dimod.binary.pybqm.pyBQM","typing.Hashable",{".class":"AnyType","missing_import_name":null,"source_any":null,"type_of_any":2}],"bound_args":[],"def_extras":{"first_arg":"self"},"fallback":"builtins.function","from_concatenate":false,"implicit":false,"imprecise_arg_kinds":false,"is_ellipsis_args":false,"name":"set_linear of pyBQM","ret_type":{".class":"AnyType","missing_import_name":null,"source_any":null,"type_of_any":1},"type_guard":null,"type_is":null,"unpack_kwargs":false,"variables":[]}}},"set_quadratic":{".class":"SymbolTableNode","kind":"Mdef","node":{".class":"FuncDef","abstract_status":0,"arg_kinds":[0,0,0,0],"arg_names":["self","u","v","bias"],"dataclass_transform_spec":null,"deprecated":null,"flags":[],"fullname":"dimod.binary.pybqm.pyBQM.set_quadratic","name":"set_quadratic","type":{".class":"CallableType","arg_kinds":[0,0,0,0],"arg_names":["self","u","v","bias"],"arg_types":["dimod.binary.pybqm.pyBQM","typing.Hashable","typing.Hashable",{".class":"AnyType","missing_import_name":null,"source_any":null,"type_of_any":2}],"bound_args":[],"def_extras":{"first_arg":"self"},"fallback":"builtins.function","from_concatenate":false,"implicit":false,"imprecise_arg_kinds":false,"is_ellipsis_args":false,"name":"set_quadratic of pyBQM","ret_type":{".class":"AnyType","missing_import_name":null,"source_any":null,"type_of_any":1},"type_guard":null,"type_is":null,"unpack_kwargs":false,"variables":[]}}},"to_numpy_vectors":{".class":"SymbolTableNode","kind":"Mdef","node":{".class":"FuncDef","abstract_status":0,"arg_kinds":[0,2,4],"arg_names":["self","args","kwargs"],"dataclass_transform_spec":null,"deprecated":null,"flags":[],"fullname":"dimod.binary.pybqm.pyBQM.to_numpy_vectors","name":"to_numpy_vectors","type":null}},"update":{".class":"SymbolTableNode","kind":"Mdef","node":{".class":"FuncDef","abstract_status":0,"arg_kinds":[0,2,4],"arg_names":["self","args","kwargs"],"dataclass_transform_spec":null,"deprecated":null,"flags":[],"fullname":"dimod.binary.pybqm.pyBQM.update","name":"update","type":null}},"variables":{".class":"SymbolTableNode","kind":"Mdef","node":{".class":"Decorator","func":{".class":"FuncDef","abstract_status":0,"arg_kinds":[0],"arg_names":["self"],"dataclass_transform_spec":null,"deprecated":null,"flags":["is_property","is_decorated"],"fullname":"dimod.binary.pybqm.pyBQM.variables","name":"variables","type":{".class":"CallableType","arg_kinds":[0],"arg_names":["self"],"arg_types":["dimod.binary.pybqm.pyBQM"],"bound_args":[],"def_extras":{"first_arg":"self"},"fallback":"builtins.function","from_concatenate":false,"implicit":false,"imprecise_arg_kinds":false,"is_ellipsis_args":false,"name":"variables of pyBQM","ret_type":{".class":"Instance","args":[{".class":"AnyType","missing_import_name":null,"source_any":null,"type_of_any":4}],"extra_attrs":null,"type_ref":"typing.Collection"},"type_guard":null,"type_is":null,"unpack_kwargs":false,"variables":[]}},"is_overload":false,"var":{".class":"Var","flags":["is_initialized_in_class","is_property","is_ready","is_inferred"],"fullname":"dimod.binary.pybqm.pyBQM.variables","name":"variables","type":{".class":"CallableType","arg_kinds":[0],"arg_names":["self"],"arg_types":["dimod.binary.pybqm.pyBQM"],"bound_args":[],"def_extras":{"first_arg":"self"},"fallback":"builtins.function","from_concatenate":false,"implicit":false,"imprecise_arg_kinds":false,"is_ellipsis_args":false,"name":"variables of pyBQM","ret_type":{".class":"Instance","args":[{".class":"AnyType","missing_import_name":null,"source_any":null,"type_of_any":4}],"extra_attrs":null,"type_ref":"typing.Collection"},"type_guard":null,"type_is":null,"unpack_kwargs":false,"variables":[]}}}},"vartype":{".class":"SymbolTableNode","kind":"Mdef","node":{".class":"FuncDef","abstract_status":0,"arg_kinds":[0,1],"arg_names":["self","v"],"dataclass_transform_spec":null,"deprecated":null,"flags":[],"fullname":"dimod.binary.pybqm.pyBQM.vartype","name":"vartype","type":{".class":"CallableType","arg_kinds":[0,1],"arg_names":["self","v"],"arg_types":["dimod.binary.pybqm.pyBQM",{".class":"UnionType","items":["typing.Hashable",{".class":"NoneType"}],"uses_pep604_syntax":false}],"bound_args":[],"def_extras":{"first_arg":"self"},"fallback":"builtins.function","from_concatenate":false,"implicit":false,"imprecise_arg_kinds":false,"is_ellipsis_args":false,"name":"vartype of pyBQM","ret_type":"dimod.vartypes.Vartype","type_guard":null,"type_is":null,"unpack_kwargs":false,"variables":[]}}}},"self_type":{".class":"TypeVarType","default":{".class":"AnyType","missing_import_name":null,"source_any":null,"type_of_any":4},"fullname":"dimod.binary.pybqm.pyBQM.Self","id":0,"name":"Self","namespace":"","upper_bound":"dimod.binary.pybqm.pyBQM","values":[],"variance":0},"slots":null,"tuple_type":null,"type_vars":[],"typeddict_type":null}},"reduce":{".class":"SymbolTableNode","cross_ref":"functools.reduce","kind":"Gdef"},"typing":{".class":"SymbolTableNode","cross_ref":"typing","kind":"Gdef"}},"path":"c:\\Users\\basia\\anaconda3\\envs\\qomm_env\\lib\\site-packages\\dimod\\binary\\pybqm.py"}