{"data_mtime":1746628447,"dep_lines":[16,6,8,13,14,15,18,19,20,4396,4695,4697,4802,4923,5,12,17,1,2,1,1,1,1,1,1,1,1,1,1,1,1],"dep_prios":[5,5,5,5,5,5,5,5,5,20,20,20,20,20,5,5,5,5,5,5,20,30,30,30,30,30,30,30,30,30,30],"dependencies":["sympy.functions.combinatorial.factorials","sympy.combinatorics.permutations","sympy.combinatorics.util","sympy.core.random","sympy.core.symbol","sympy.core.sympify","sympy.ntheory.factor_","sympy.ntheory.primetest","sympy.utilities.iterables","sympy.combinatorics.homomorphisms","sympy.combinatorics.fp_groups","sympy.combinatorics.free_groups","sympy.combinatorics.coset_table","sympy.combinatorics.pc_groups","sympy.combinatorics","sympy.core","sympy.ntheory","math","itertools","builtins","typing","_frozen_importlib","_typeshed","abc","sympy.core._print_helpers","sympy.core.assumptions","sympy.core.basic","sympy.core.core","sympy.functions","sympy.functions.combinatorial","sympy.ntheory.generate"],"hash":"b0e14e33c3ad136d99b60803c8413fcd3d911666","id":"sympy.combinatorics.perm_groups","ignore_all":true,"interface_hash":"46ea31de014cdafc53dbcb4e49fb68b81c60f947","mtime":1720809503,"options":{"allow_redefinition":false,"allow_untyped_globals":false,"always_false":[],"always_true":[],"bazel":false,"check_untyped_defs":true,"disable_bytearray_promotion":false,"disable_error_code":[],"disable_memoryview_promotion":false,"disabled_error_codes":[],"disallow_any_decorated":false,"disallow_any_explicit":false,"disallow_any_expr":false,"disallow_any_generics":false,"disallow_any_unimported":false,"disallow_incomplete_defs":false,"disallow_subclassing_any":false,"disallow_untyped_calls":true,"disallow_untyped_decorators":false,"disallow_untyped_defs":true,"enable_error_code":[],"enabled_error_codes":[],"extra_checks":false,"follow_imports":"normal","follow_imports_for_stubs":false,"follow_untyped_imports":false,"ignore_errors":false,"ignore_missing_imports":true,"implicit_optional":false,"implicit_reexport":true,"local_partial_types":false,"mypyc":false,"old_type_inference":false,"platform":"win32","plugins":[],"strict_bytes":false,"strict_concatenate":false,"strict_equality":false,"strict_optional":true,"warn_no_return":true,"warn_return_any":true,"warn_unreachable":false,"warn_unused_ignores":true},"path":"c:\\Users\\basia\\anaconda3\\envs\\qomm_env\\lib\\site-packages\\sympy\\combinatorics\\perm_groups.py","plugin_data":null,"size":182040,"suppressed":[],"version_id":"1.15.0"}