{".class":"MypyFile","_fullname":"QHyper.constraint","future_import_flags":[],"is_partial_stub_package":false,"is_stub":false,"names":{".class":"SymbolTable","Constraint":{".class":"SymbolTableNode","kind":"Gdef","node":{".class":"TypeInfo","_promote":[],"abstract_attributes":[],"alt_promote":null,"bases":["builtins.object"],"dataclass_transform_spec":null,"declared_metaclass":null,"defn":{".class":"ClassDef","fullname":"QHyper.constraint.Constraint","name":"Constraint","type_vars":[]},"deletable_attributes":[],"deprecated":null,"flags":[],"fullname":"QHyper.constraint.Constraint","has_param_spec_type":false,"metaclass_type":null,"metadata":{},"module_name":"QHyper.constraint","mro":["QHyper.constraint.Constraint","builtins.object"],"names":{".class":"SymbolTable","__init__":{".class":"SymbolTableNode","kind":"Mdef","node":{".class":"FuncDef","abstract_status":0,"arg_kinds":[0,0,1,1,1,1,1],"arg_names":["self","lhs","rhs","operator","method_for_inequalities","label","group"],"dataclass_transform_spec":null,"deprecated":null,"flags":[],"fullname":"QHyper.constraint.Constraint.__init__","name":"__init__","type":{".class":"CallableType","arg_kinds":[0,0,1,1,1,1,1],"arg_names":["self","lhs","rhs","operator","method_for_inequalities","label","group"],"arg_types":["QHyper.constraint.Constraint",{".class":"TypeAliasType","args":[],"type_ref":"QHyper.polynomial.PolynomialType"},{".class":"TypeAliasType","args":[],"type_ref":"QHyper.polynomial.PolynomialType"},"QHyper.constraint.Operator",{".class":"UnionType","items":["QHyper.constraint.MethodsForInequalities",{".class":"NoneType"}],"uses_pep604_syntax":true},"builtins.str","builtins.int"],"bound_args":[],"def_extras":{"first_arg":"self"},"fallback":"builtins.function","from_concatenate":false,"implicit":false,"imprecise_arg_kinds":false,"is_ellipsis_args":false,"name":"__init__ of Constraint","ret_type":{".class":"NoneType"},"type_guard":null,"type_is":null,"unpack_kwargs":false,"variables":[]}}},"__repr__":{".class":"SymbolTableNode","kind":"Mdef","node":{".class":"FuncDef","abstract_status":0,"arg_kinds":[0],"arg_names":[null],"dataclass_transform_spec":null,"deprecated":null,"flags":[],"fullname":"QHyper.constraint.Constraint.__repr__","name":"__repr__","type":{".class":"CallableType","arg_kinds":[0],"arg_names":[null],"arg_types":["QHyper.constraint.Constraint"],"bound_args":[],"def_extras":{"first_arg":"self"},"fallback":"builtins.function","from_concatenate":false,"implicit":false,"imprecise_arg_kinds":false,"is_ellipsis_args":false,"name":"__repr__ of Constraint","ret_type":"builtins.str","type_guard":null,"type_is":null,"unpack_kwargs":false,"variables":[]}}},"_set_label":{".class":"SymbolTableNode","kind":"Mdef","node":{".class":"FuncDef","abstract_status":0,"arg_kinds":[0,0],"arg_names":["self","label"],"dataclass_transform_spec":null,"deprecated":null,"flags":[],"fullname":"QHyper.constraint.Constraint._set_label","name":"_set_label","type":{".class":"CallableType","arg_kinds":[0,0],"arg_names":["self","label"],"arg_types":["QHyper.constraint.Constraint","builtins.str"],"bound_args":[],"def_extras":{"first_arg":"self"},"fallback":"builtins.function","from_concatenate":false,"implicit":false,"imprecise_arg_kinds":false,"is_ellipsis_args":false,"name":"_set_label of Constraint","ret_type":{".class":"NoneType"},"type_guard":null,"type_is":null,"unpack_kwargs":false,"variables":[]}}},"get_variables":{".class":"SymbolTableNode","kind":"Mdef","node":{".class":"FuncDef","abstract_status":0,"arg_kinds":[0],"arg_names":["self"],"dataclass_transform_spec":null,"deprecated":null,"flags":[],"fullname":"QHyper.constraint.Constraint.get_variables","name":"get_variables","type":{".class":"CallableType","arg_kinds":[0],"arg_names":["self"],"arg_types":["QHyper.constraint.Constraint"],"bound_args":[],"def_extras":{"first_arg":"self"},"fallback":"builtins.function","from_concatenate":false,"implicit":false,"imprecise_arg_kinds":false,"is_ellipsis_args":false,"name":"get_variables of Constraint","ret_type":{".class":"Instance","args":["builtins.str"],"extra_attrs":null,"type_ref":"builtins.set"},"type_guard":null,"type_is":null,"unpack_kwargs":false,"variables":[]}}},"group":{".class":"SymbolTableNode","implicit":true,"kind":"Mdef","node":{".class":"Var","flags":["is_inferred"],"fullname":"QHyper.constraint.Constraint.group","name":"group","type":"builtins.int"}},"label":{".class":"SymbolTableNode","implicit":true,"kind":"Mdef","node":{".class":"Var","flags":["is_inferred"],"fullname":"QHyper.constraint.Constraint.label","name":"label","type":"builtins.str"}},"lhs":{".class":"SymbolTableNode","implicit":true,"kind":"Mdef","node":{".class":"Var","flags":["is_inferred"],"fullname":"QHyper.constraint.Constraint.lhs","name":"lhs","type":"QHyper.polynomial.Polynomial"}},"method_for_inequalities":{".class":"SymbolTableNode","implicit":true,"kind":"Mdef","node":{".class":"Var","flags":["is_inferred"],"fullname":"QHyper.constraint.Constraint.method_for_inequalities","name":"method_for_inequalities","type":{".class":"UnionType","items":["QHyper.constraint.MethodsForInequalities",{".class":"NoneType"}],"uses_pep604_syntax":true}}},"operator":{".class":"SymbolTableNode","implicit":true,"kind":"Mdef","node":{".class":"Var","flags":["explicit_self_type","is_ready","is_inferred"],"fullname":"QHyper.constraint.Constraint.operator","name":"operator","type":"QHyper.constraint.Operator"}},"rhs":{".class":"SymbolTableNode","implicit":true,"kind":"Mdef","node":{".class":"Var","flags":["is_inferred"],"fullname":"QHyper.constraint.Constraint.rhs","name":"rhs","type":"QHyper.polynomial.Polynomial"}}},"self_type":{".class":"TypeVarType","default":{".class":"AnyType","missing_import_name":null,"source_any":null,"type_of_any":4},"fullname":"QHyper.constraint.Constraint.Self","id":0,"name":"Self","namespace":"","upper_bound":"QHyper.constraint.Constraint","values":[],"variance":0},"slots":null,"tuple_type":null,"type_vars":[],"typeddict_type":null}},"Enum":{".class":"SymbolTableNode","cross_ref":"enum.Enum","kind":"Gdef"},"MethodsForInequalities":{".class":"SymbolTableNode","kind":"Gdef","node":{".class":"TypeInfo","_promote":[],"abstract_attributes":[],"alt_promote":null,"bases":["enum.Enum"],"dataclass_transform_spec":null,"declared_metaclass":null,"defn":{".class":"ClassDef","fullname":"QHyper.constraint.MethodsForInequalities","name":"MethodsForInequalities","type_vars":[]},"deletable_attributes":[],"deprecated":null,"flags":["is_enum"],"fullname":"QHyper.constraint.MethodsForInequalities","has_param_spec_type":false,"metaclass_type":"enum.EnumMeta","metadata":{},"module_name":"QHyper.constraint","mro":["QHyper.constraint.MethodsForInequalities","enum.Enum","builtins.object"],"names":{".class":"SymbolTable","SLACKS_LOG_2":{".class":"SymbolTableNode","kind":"Mdef","node":{".class":"Var","flags":["is_initialized_in_class","is_final","is_ready","is_inferred","has_explicit_value"],"fullname":"QHyper.constraint.MethodsForInequalities.SLACKS_LOG_2","name":"SLACKS_LOG_2","type":{".class":"Instance","args":[],"extra_attrs":null,"last_known_value":{".class":"LiteralType","fallback":"builtins.int","value":0},"type_ref":"builtins.int"}}},"UNBALANCED_PENALIZATION":{".class":"SymbolTableNode","kind":"Mdef","node":{".class":"Var","flags":["is_initialized_in_class","is_final","is_ready","is_inferred","has_explicit_value"],"fullname":"QHyper.constraint.MethodsForInequalities.UNBALANCED_PENALIZATION","name":"UNBALANCED_PENALIZATION","type":{".class":"Instance","args":[],"extra_attrs":null,"last_known_value":{".class":"LiteralType","fallback":"builtins.int","value":1},"type_ref":"builtins.int"}}}},"self_type":{".class":"TypeVarType","default":{".class":"AnyType","missing_import_name":null,"source_any":null,"type_of_any":4},"fullname":"QHyper.constraint.MethodsForInequalities.Self","id":0,"name":"Self","namespace":"","upper_bound":"QHyper.constraint.MethodsForInequalities","values":[],"variance":0},"slots":null,"tuple_type":null,"type_vars":[],"typeddict_type":null}},"Operator":{".class":"SymbolTableNode","kind":"Gdef","node":{".class":"TypeInfo","_promote":[],"abstract_attributes":[],"alt_promote":null,"bases":["enum.Enum"],"dataclass_transform_spec":null,"declared_metaclass":null,"defn":{".class":"ClassDef","fullname":"QHyper.constraint.Operator","name":"Operator","type_vars":[]},"deletable_attributes":[],"deprecated":null,"flags":["is_enum"],"fullname":"QHyper.constraint.Operator","has_param_spec_type":false,"metaclass_type":"enum.EnumMeta","metadata":{},"module_name":"QHyper.constraint","mro":["QHyper.constraint.Operator","enum.Enum","builtins.object"],"names":{".class":"SymbolTable","EQ":{".class":"SymbolTableNode","kind":"Mdef","node":{".class":"Var","flags":["is_initialized_in_class","is_final","is_ready","is_inferred","has_explicit_value"],"fullname":"QHyper.constraint.Operator.EQ","name":"EQ","type":{".class":"Instance","args":[],"extra_attrs":null,"last_known_value":{".class":"LiteralType","fallback":"builtins.str","value":"=="},"type_ref":"builtins.str"}}},"GE":{".class":"SymbolTableNode","kind":"Mdef","node":{".class":"Var","flags":["is_initialized_in_class","is_final","is_ready","is_inferred","has_explicit_value"],"fullname":"QHyper.constraint.Operator.GE","name":"GE","type":{".class":"Instance","args":[],"extra_attrs":null,"last_known_value":{".class":"LiteralType","fallback":"builtins.str","value":">="},"type_ref":"builtins.str"}}},"LE":{".class":"SymbolTableNode","kind":"Mdef","node":{".class":"Var","flags":["is_initialized_in_class","is_final","is_ready","is_inferred","has_explicit_value"],"fullname":"QHyper.constraint.Operator.LE","name":"LE","type":{".class":"Instance","args":[],"extra_attrs":null,"last_known_value":{".class":"LiteralType","fallback":"builtins.str","value":"<="},"type_ref":"builtins.str"}}}},"self_type":{".class":"TypeVarType","default":{".class":"AnyType","missing_import_name":null,"source_any":null,"type_of_any":4},"fullname":"QHyper.constraint.Operator.Self","id":0,"name":"Self","namespace":"","upper_bound":"QHyper.constraint.Operator","values":[],"variance":0},"slots":null,"tuple_type":null,"type_vars":[],"typeddict_type":null}},"Polynomial":{".class":"SymbolTableNode","cross_ref":"QHyper.polynomial.Polynomial","kind":"Gdef"},"PolynomialType":{".class":"SymbolTableNode","cross_ref":"QHyper.polynomial.PolynomialType","kind":"Gdef"},"SLACKS_LOG_2":{".class":"SymbolTableNode","kind":"Gdef","node":{".class":"Var","flags":["is_inferred","has_explicit_value"],"fullname":"QHyper.constraint.SLACKS_LOG_2","name":"SLACKS_LOG_2","type":"QHyper.constraint.MethodsForInequalities"}},"UNBALANCED_PENALIZATION":{".class":"SymbolTableNode","kind":"Gdef","node":{".class":"Var","flags":["is_inferred","has_explicit_value"],"fullname":"QHyper.constraint.UNBALANCED_PENALIZATION","name":"UNBALANCED_PENALIZATION","type":"QHyper.constraint.MethodsForInequalities"}},"__annotations__":{".class":"SymbolTableNode","kind":"Gdef","node":{".class":"Var","flags":["is_ready"],"fullname":"QHyper.constraint.__annotations__","name":"__annotations__","type":{".class":"Instance","args":["builtins.str",{".class":"AnyType","missing_import_name":null,"source_any":null,"type_of_any":6}],"extra_attrs":null,"type_ref":"builtins.dict"}}},"__doc__":{".class":"SymbolTableNode","kind":"Gdef","node":{".class":"Var","flags":["is_ready"],"fullname":"QHyper.constraint.__doc__","name":"__doc__","type":"builtins.str"}},"__file__":{".class":"SymbolTableNode","kind":"Gdef","node":{".class":"Var","flags":["is_ready"],"fullname":"QHyper.constraint.__file__","name":"__file__","type":"builtins.str"}},"__name__":{".class":"SymbolTableNode","kind":"Gdef","node":{".class":"Var","flags":["is_ready"],"fullname":"QHyper.constraint.__name__","name":"__name__","type":"builtins.str"}},"__package__":{".class":"SymbolTableNode","kind":"Gdef","node":{".class":"Var","flags":["is_ready"],"fullname":"QHyper.constraint.__package__","name":"__package__","type":"builtins.str"}},"__spec__":{".class":"SymbolTableNode","kind":"Gdef","node":{".class":"Var","flags":["is_ready"],"fullname":"QHyper.constraint.__spec__","name":"__spec__","type":"_frozen_importlib.ModuleSpec"}},"get_number_of_constraints":{".class":"SymbolTableNode","kind":"Gdef","node":{".class":"FuncDef","abstract_status":0,"arg_kinds":[0],"arg_names":["constraints"],"dataclass_transform_spec":null,"deprecated":null,"flags":[],"fullname":"QHyper.constraint.get_number_of_constraints","name":"get_number_of_constraints","type":{".class":"CallableType","arg_kinds":[0],"arg_names":["constraints"],"arg_types":[{".class":"Instance","args":["QHyper.constraint.Constraint"],"extra_attrs":null,"type_ref":"builtins.list"}],"bound_args":[],"def_extras":{"first_arg":null},"fallback":"builtins.function","from_concatenate":false,"implicit":false,"imprecise_arg_kinds":false,"is_ellipsis_args":false,"name":"get_number_of_constraints","ret_type":"builtins.int","type_guard":null,"type_is":null,"unpack_kwargs":false,"variables":[]}}},"uuid":{".class":"SymbolTableNode","cross_ref":"uuid","kind":"Gdef"}},"path":"C:\\Users\\basia\\Desktop\\Praca_Inzynierska_2024\\QHyper\\QHyper\\constraint.py"}